eadred-0.3.dist-info/WHEEL
eadred-0.3.dist-info/top_level.txt
eadred-0.3.dist-info/RECORD
eadred-0.3.dist-info/METADATA
eadred-0.3.dist-info/metadata.json
eadred-0.3.dist-info/DESCRIPTION.rst
eadred/helpers.py
eadred/__init__.py
eadred/_version.py
eadred/management/__init__.py
eadred/management/commands/generatedata.py
eadred/management/commands/__init__.py
eadred/tests/test_helpers.py
eadred/tests/__init__.py
eadred/tests/test_generate.py
eadred/data/domains.txt
eadred/data/lorem_ipsum.txt
eadred/data/english_monarchs.txt
