Metadata-Version: 2.0
Name: eadred
Version: 0.3
Summary: Django app for generating sample data
Home-page: https://github.com/willkg/django-eadred
Author: Will Kahn-Greene
Author-email: willg@bluesock.org
License: BSD
Platform: UNKNOWN
Classifier: Development Status :: 4 - Beta
Classifier: Environment :: Web Environment
Classifier: Framework :: Django
Classifier: Intended Audience :: Developers
Classifier: License :: OSI Approved :: BSD License
Classifier: Operating System :: OS Independent
Classifier: Programming Language :: Python
Classifier: Programming Language :: Python :: 2.6
Classifier: Programming Language :: Python :: 2.7
Classifier: Topic :: Software Development :: Libraries :: Python Modules
Classifier: Natural Language :: English
